licensekey2/__init__.py
licensekey2/exceptions.py
licensekey2/license/__init__.py
licensekey2/license/abstract.py
licensekey2/license/crypto.py
licensekey2/license/remote.py
licensekey2/types.py
licensekey2-0.1.0.dist-info/LICENSE
licensekey2-0.1.0.dist-info/WHEEL
licensekey2-0.1.0.dist-info/METADATA
licensekey2-0.1.0.dist-info/RECORD
