Metadata-Version: 2.1
Name: licensekey2
Version: 0.1.0
Summary: Licensing library
Home-page: https://git.frsqr.xyz/cofob/license-key
License: MIT
Keywords: license,licensing
Author: Egor Ternovoy
Author-email: cofob@riseup.net
Requires-Python: >=3.8,<4.0
Classifier: License :: OSI Approved :: MIT License
Classifier: Programming Language :: Python :: 3
Classifier: Programming Language :: Python :: 3.10
Classifier: Programming Language :: Python :: 3.8
Classifier: Programming Language :: Python :: 3.9
Provides-Extra: crypto
Provides-Extra: requests
Requires-Dist: cryptography (>=38,<39); extra == "crypto"
Requires-Dist: requests (>=2.28,<3.0); extra == "requests"
Project-URL: Repository, https://git.frsqr.xyz/cofob/license-key
